fsbi/__init__.py
fsbi-0.4.dist-info/METADATA
fsbi-0.4.dist-info/WHEEL
fsbi-0.4.dist-info/entry_points.txt
fsbi-0.4.dist-info/top_level.txt
fsbi-0.4.dist-info/RECORD
