Metadata-Version: 2.1
Name: fsbi
Version: 0.4
Summary: Font Stretch Bold Italic
Home-page: http://phyl.io/?page=fsbi.html
Author: Philippe Kappel
Author-email: philippe.kappel@gmail.com
License: MIT
Keywords: font
Classifier: Development Status :: 3 - Alpha
Classifier: Environment :: Console
Classifier: Intended Audience :: Developers
Classifier: Intended Audience :: End Users/Desktop
Classifier: Intended Audience :: System Administrators
Classifier: License :: OSI Approved :: MIT License
Classifier: Natural Language :: English
Classifier: Operating System :: OS Independent
Classifier: Programming Language :: Python :: 3
Classifier: Topic :: System :: Console Fonts
Classifier: Topic :: Text Processing :: Fonts
Classifier: Topic :: Utilities
